pycellga/__init__.py
pycellga/byte_operators.py
pycellga/common.py
pycellga/grid.py
pycellga/individual.py
pycellga/optimizer.py
pycellga/population.py
pycellga/example/__init__.py
pycellga/example/example_alpha_cga.py
pycellga/example/example_ccga.py
pycellga/example/example_cga.py
pycellga/example/example_mcccga.py
pycellga/example/example_sync_cga.py
pycellga/mutation/__init__.py
pycellga/mutation/bit_flip_mutation.py
pycellga/mutation/byte_mutation.py
pycellga/mutation/byte_mutation_random.py
pycellga/mutation/float_uniform_mutation.py
pycellga/mutation/insertion_mutation.py
pycellga/mutation/mutation_operator.py
pycellga/mutation/shuffle_mutation.py
pycellga/mutation/swap_mutation.py
pycellga/mutation/two_opt_mutation.py
pycellga/neighborhoods/__init__.py
pycellga/neighborhoods/compact_13.py
pycellga/neighborhoods/compact_21.py
pycellga/neighborhoods/compact_25.py
pycellga/neighborhoods/compact_9.py
pycellga/neighborhoods/linear_5.py
pycellga/neighborhoods/linear_9.py
pycellga/problems/__init__.py
pycellga/problems/abstract_problem.py
pycellga/problems/single_objective/__init__.py
pycellga/problems/single_objective/continuous/__init__.py
pycellga/problems/single_objective/continuous/ackley.py
pycellga/problems/single_objective/continuous/bentcigar.py
pycellga/problems/single_objective/continuous/bohachevsky.py
pycellga/problems/single_objective/continuous/chichinadze.py
pycellga/problems/single_objective/continuous/dropwave.py
pycellga/problems/single_objective/continuous/fms.py
pycellga/problems/single_objective/continuous/griewank.py
pycellga/problems/single_objective/continuous/holzman.py
pycellga/problems/single_objective/continuous/levy.py
pycellga/problems/single_objective/continuous/matyas.py
pycellga/problems/single_objective/continuous/pow.py
pycellga/problems/single_objective/continuous/powell.py
pycellga/problems/single_objective/continuous/rastrigin.py
pycellga/problems/single_objective/continuous/rosenbrock.py
pycellga-0.4.0.dist-info/LICENSE
pycellga-0.4.0.dist-info/METADATA
pycellga-0.4.0.dist-info/WHEEL
pycellga-0.4.0.dist-info/top_level.txt
pycellga-0.4.0.dist-info/RECORD
