Metadata-Version: 2.1
Name: pycellga
Version: 0.4.0
Summary: A Python Package for Improved Cellular Genetic Algorithms
Home-page: https://github.com/SevgiAkten/pycellga
Author: Sevgi Akten Karakaya, Mehmet Hakan Satman
Author-email: sevgiakten@gmail.com, mhsatman@gmail.com
Project-URL: Documentation, https://sevgiakten.github.io/pycellga/
Project-URL: Source, https://github.com/SevgiAkten/pycellga
Project-URL: Issue Tracker, https://github.com/SevgiAkten/pycellga/issues
Project-URL: PyPI, https://pypi.org/project/pycellga/
Classifier: Programming Language :: Python :: 3
Classifier: License :: OSI Approved :: MIT License
Classifier: Operating System :: OS Independent
Requires-Python: >=3.6
License-File: LICENSE
Requires-Dist: geographiclib<3.0,>=2.0
Requires-Dist: geopy<3.0,>=2.4.0
Requires-Dist: iniconfig<3.0,>=2.0.0
Requires-Dist: mpmath<2.0,>=1.3.0
Requires-Dist: numpy<2.0,>=1.26.0
Requires-Dist: plumbum<2.0,>=1.8.3
Requires-Dist: ply<4.0,>=3.11
Requires-Dist: pyparsing<4.0,>=3.1.1
Requires-Dist: python-dateutil<3.0,>=2.8.0
Requires-Dist: pytz<2024.0,>=2023.3
Requires-Dist: tzdata<2024.0,>=2023.3
Requires-Dist: pymoo<1.0,>=0.5.0
Requires-Dist: tsplib95<1.0,>=0.7.0
Provides-Extra: dev
Requires-Dist: pytest<9.0,>=8.0; extra == "dev"
Requires-Dist: pytest-xdist<4.0,>=3.0; extra == "dev"
Requires-Dist: grip==4.6.2; extra == "dev"
Requires-Dist: Markdown==3.6; extra == "dev"
Requires-Dist: Markdown-Editor==1.0.7; extra == "dev"
Requires-Dist: path-and-address==2.0.1; extra == "dev"
Requires-Dist: pluggy==1.5.0; extra == "dev"
Requires-Dist: six==1.16.0; extra == "dev"
Provides-Extra: docs
Requires-Dist: sphinx<8.0,>=7.4.0; extra == "docs"
Requires-Dist: sphinx-rtd-theme<3.0,>=2.0.0; extra == "docs"
Requires-Dist: sphinxcontrib-applehelp<3.0,>=2.0.0; extra == "docs"
Requires-Dist: sphinxcontrib-htmlhelp<3.0,>=2.1.0; extra == "docs"
Requires-Dist: sphinxcontrib-jquery<5.0,>=4.1; extra == "docs"
Requires-Dist: sphinxcontrib-jsmath<2.0,>=1.0.0; extra == "docs"
Requires-Dist: sphinxcontrib-qthelp<3.0,>=2.0.0; extra == "docs"
Requires-Dist: sphinxcontrib-serializinghtml<3.0,>=2.0.0; extra == "docs"
